agents/ben_graham.py
agents/bill_ackman.py
agents/cathie_wood.py
agents/charlie_munger.py
agents/fundamentals.py
agents/portfolio_manager.py
agents/risk_manager.py
agents/sentiment.py
agents/technicals.py
agents/valuation.py
agents/warren_buffett.py
src/backtester.py
data/cache.py
data/models.py
graph/state.py
llm/models.py
src/main.py
tools/api.py
utils/__init__.py
utils/analysts.py
utils/display.py
utils/llm.py
utils/progress.py
utils/visualize.py
ai_rich-0.1.5.dist-info/LICENSE
ai_rich-0.1.5.dist-info/METADATA
ai_rich-0.1.5.dist-info/WHEEL
ai_rich-0.1.5.dist-info/entry_points.txt
ai_rich-0.1.5.dist-info/RECORD
