Metadata-Version: 2.1
Name: ai-rich
Version: 0.1.5
Summary: An AI-powered hedge fund that uses multiple agents to make trading decisions
Author: fanxi
Author-email: fanxi@gmail.com
Requires-Python: >=3.9,<4.0
Classifier: Programming Language :: Python :: 3
Classifier: Programming Language :: Python :: 3.9
Classifier: Programming Language :: Python :: 3.10
Classifier: Programming Language :: Python :: 3.11
Classifier: Programming Language :: Python :: 3.12
Classifier: Programming Language :: Python :: 3.13
Requires-Dist: colorama (>=0.4.6,<0.5.0)
Requires-Dist: httpx[socks] (>=0.28.1,<0.29.0)
Requires-Dist: langchain (==0.3.0)
Requires-Dist: langchain-anthropic (==0.3.5)
Requires-Dist: langchain-groq (==0.2.3)
Requires-Dist: langchain-openai (==0.3)
Requires-Dist: langgraph (==0.2.56)
Requires-Dist: matplotlib (>=3.9.2,<4.0.0)
Requires-Dist: numpy (>=1.24.0,<2.0.0)
Requires-Dist: pandas (>=2.1.0,<3.0.0)
Requires-Dist: python-dotenv (==1.0.0)
Requires-Dist: questionary (>=2.1.0,<3.0.0)
Requires-Dist: rich (>=13.9.4,<14.0.0)
Requires-Dist: tabulate (>=0.9.0,<0.10.0)
